{
    "bot_id": "HL_INTEGRATED_MASTER",
    "equity": 104.46,
    "z_scores": {
        "xyz:HOOD": {
            "val": 0.46,
            "atr": 0.0463,
            "trend_1h": "UP",
            "trend_4h": "UP",
            "updated_at": "06:01:19"
        },
        "xyz:PLATINUM": {
            "val": -1.91,
            "atr": 0.2,
            "trend_1h": "UP",
            "trend_4h": "UP",
            "updated_at": "06:01:19"
        },
        "xyz:BABA": {
            "val": 1.01,
            "atr": 0.0043,
            "trend_1h": "UP",
            "trend_4h": "DOWN",
            "updated_at": "06:01:19"
        },
        "xyz:AMD": {
            "val": 0.93,
            "atr": 0.1107,
            "trend_1h": "UP",
            "trend_4h": "DOWN",
            "updated_at": "06:01:20"
        },
        "xyz:GME": {
            "val": -0.51,
            "atr": 0.0098,
            "trend_1h": "DOWN",
            "trend_4h": "DOWN",
            "updated_at": "06:01:20"
        },
        "xyz:EWJ": {
            "val": -2.92,
            "atr": 0.0144,
            "trend_1h": "DOWN",
            "trend_4h": "UP",
            "updated_at": "06:01:20"
        },
        "xyz:COPPER": {
            "val": -0.71,
            "atr": 0.0013,
            "trend_1h": "UP",
            "trend_4h": "DOWN",
            "updated_at": "06:01:21"
        },
        "xyz:XYZ100": {
            "val": -0.08,
            "atr": 3.0714,
            "trend_1h": "UP",
            "trend_4h": "DOWN",
            "updated_at": "06:01:21"
        },
        "UNI": {
            "val": 1.21,
            "atr": 0.0016,
            "trend_1h": "DOWN",
            "trend_4h": "DOWN",
            "updated_at": "06:01:21"
        },
        "LDO": {
            "val": -0.96,
            "atr": 0.0002,
            "trend_1h": "DOWN",
            "trend_4h": "DOWN",
            "updated_at": "06:01:22"
        },
        "LINK": {
            "val": 0.36,
            "atr": 0.0047,
            "trend_1h": "DOWN",
            "trend_4h": "DOWN",
            "updated_at": "06:01:22"
        },
        "NEO": {
            "val": 0.88,
            "atr": 0.0017,
            "trend_1h": "DOWN",
            "trend_4h": "DOWN",
            "updated_at": "06:01:23"
        },
        "CRV": {
            "val": -0.86,
            "atr": 0.0001,
            "trend_1h": "DOWN",
            "trend_4h": "DOWN",
            "updated_at": "06:01:23"
        },
        "PYTH": {
            "val": 0.14,
            "atr": 0.0,
            "trend_1h": "DOWN",
            "trend_4h": "DOWN",
            "updated_at": "06:01:23"
        }
    },
    "active_positions": {
        "LDO": {
            "side": -1,
            "entry_p": 0.3226,
            "size": 384.3,
            "entry_size": 384.3,
            "tp": 0.015,
            "sl": -0.025,
            "entry_time": 1780067434.681376,
            "accumulated_pnl": 0.0,
            "tp_p": 0.31776,
            "sl_p": 0.33066,
            "effective_lev": 5.0,
            "hwm": 0.94,
            "hwm_p": 0.31956,
            "in_trail": false,
            "unrealizedPnl": 0.66,
            "roe": 2.67,
            "tp_roe": 7.5,
            "sl_roe": -12.5,
            "trail_start": 1.05,
            "trail_exit_p": 0.32053,
            "curr_p": 0.32088,
            "target_lev": 5
        },
        "CRV": {
            "side": -1,
            "entry_p": 0.21228,
            "size": 1161.6,
            "entry_size": 1161.6,
            "tp": 0.015,
            "sl": -0.025,
            "entry_time": 1780067466.1138952,
            "accumulated_pnl": 0.0,
            "tp_p": 0.2091,
            "sl_p": 0.21759,
            "effective_lev": 10.0,
            "hwm": 0.61,
            "hwm_p": 0.21099,
            "in_trail": false,
            "unrealizedPnl": -0.01,
            "roe": -0.05,
            "tp_roe": 15.0,
            "sl_roe": -25.0,
            "trail_start": 1.05,
            "trail_exit_p": 0.21163,
            "curr_p": 0.21229,
            "target_lev": 10.0
        },
        "LINK": {
            "side": -1,
            "entry_p": 8.9874,
            "size": 27.3,
            "entry_size": 27.3,
            "tp": 0.015,
            "sl": -0.025,
            "entry_time": 1780067498.718726,
            "accumulated_pnl": 0.0,
            "tp_p": 8.85259,
            "sl_p": 9.21208,
            "effective_lev": 10.0,
            "hwm": 0.66,
            "hwm_p": 8.9282,
            "in_trail": false,
            "unrealizedPnl": -0.5,
            "roe": -2.05,
            "tp_roe": 15.0,
            "sl_roe": -25.0,
            "trail_start": 1.05,
            "trail_exit_p": 8.95516,
            "curr_p": 9.00585,
            "target_lev": 10.0
        }
    },
    "daily_stats": {
        "pnl_usdc": 0,
        "weekly_pnl": -49.27966900000001,
        "monthly_pnl": 6.99665899999996,
        "wins": 0,
        "losses": 0,
        "asset_pnl": {},
        "date": "2026-05-30",
        "asset_losses": {}
    },
    "max_slots": 4,
    "timestamp": "2026-05-30T06:01:23.801160"
}