{
    "bot_id": "HL_INTEGRATED_MASTER",
    "equity": 87.79,
    "z_scores": {
        "xyz:HOOD": {
            "val": -1.02,
            "atr": 0.0786,
            "trend_1h": "DOWN",
            "trend_4h": "DOWN",
            "updated_at": "08:48:25"
        },
        "xyz:CL": {
            "val": -0.02,
            "atr": 0.0194,
            "trend_1h": "UP",
            "trend_4h": "UP",
            "updated_at": "08:48:24"
        },
        "DYDX": {
            "val": 0.38,
            "atr": 0.0001,
            "trend_1h": "UP",
            "trend_4h": "UP",
            "updated_at": "08:48:22"
        },
        "xyz:AMD": {
            "val": -1.32,
            "atr": 0.7493,
            "trend_1h": "DOWN",
            "trend_4h": "UP",
            "updated_at": "08:48:25"
        },
        "xyz:AAPL": {
            "val": 1.29,
            "atr": 0.0886,
            "trend_1h": "UP",
            "trend_4h": "UP",
            "updated_at": "08:48:25"
        },
        "JUP": {
            "val": -2.64,
            "atr": 0.0002,
            "trend_1h": "DOWN",
            "trend_4h": "DOWN",
            "updated_at": "08:48:23"
        },
        "xyz:GOLD": {
            "val": 0.51,
            "atr": 0.55,
            "trend_1h": "DOWN",
            "trend_4h": "DOWN",
            "updated_at": "08:48:22"
        },
        "xyz:PLATINUM": {
            "val": -1.16,
            "atr": 0.6571,
            "trend_1h": "DOWN",
            "trend_4h": "DOWN",
            "updated_at": "08:48:24"
        },
        "WIF": {
            "val": -2.21,
            "atr": 0.0001,
            "trend_1h": "DOWN",
            "trend_4h": "UP",
            "updated_at": "08:48:23"
        },
        "INJ": {
            "val": -3.02,
            "atr": 0.0048,
            "trend_1h": "DOWN",
            "trend_4h": "DOWN",
            "updated_at": "08:48:23"
        },
        "NEAR": {
            "val": -2.43,
            "atr": 0.0013,
            "trend_1h": "DOWN",
            "trend_4h": "DOWN",
            "updated_at": "08:48:24"
        },
        "ARB": {
            "val": -0.48,
            "atr": 0.0001,
            "trend_1h": "UP",
            "trend_4h": "UP",
            "updated_at": "08:48:24"
        },
        "xyz:BABA": {
            "val": -0.42,
            "atr": 0.0271,
            "trend_1h": "UP",
            "trend_4h": "DOWN",
            "updated_at": "08:48:26"
        },
        "xyz:EWZ": {
            "val": 1.25,
            "atr": 0.0005,
            "trend_1h": "UP",
            "trend_4h": "DOWN",
            "updated_at": "08:48:26"
        }
    },
    "active_positions": {},
    "daily_stats": {
        "pnl_usdc": 0,
        "weekly_pnl": 10.577955,
        "monthly_pnl": -0.9124890000000003,
        "wins": 0,
        "losses": 0,
        "asset_pnl": {},
        "date": "2026-07-17",
        "asset_losses": {}
    },
    "max_slots": 4,
    "timestamp": "2026-07-17T08:48:26.542120"
}