{
    "bot_id": "HL_INTEGRATED_MASTER",
    "equity": 91.7,
    "z_scores": {
        "xyz:BABA": {
            "val": -0.5,
            "atr": 0.0686,
            "trend_1h": "DOWN",
            "trend_4h": "UP",
            "updated_at": "20:18:06"
        },
        "xyz:COST": {
            "val": -1.43,
            "atr": 0.25,
            "trend_1h": "UP",
            "trend_4h": "UP",
            "updated_at": "20:18:08"
        },
        "xyz:LLY": {
            "val": -2.59,
            "atr": 0.2214,
            "trend_1h": "UP",
            "trend_4h": "UP",
            "updated_at": "20:18:07"
        },
        "xyz:EWZ": {
            "val": -1.18,
            "atr": 0.0191,
            "trend_1h": "DOWN",
            "trend_4h": "DOWN",
            "updated_at": "20:18:07"
        },
        "INJ": {
            "val": -2.05,
            "atr": 0.0123,
            "trend_1h": "DOWN",
            "trend_4h": "DOWN",
            "updated_at": "20:18:10"
        },
        "WIF": {
            "val": -2.82,
            "atr": 0.0003,
            "trend_1h": "DOWN",
            "trend_4h": "DOWN",
            "updated_at": "20:18:09"
        },
        "BNB": {
            "val": -2.35,
            "atr": 0.6471,
            "trend_1h": "DOWN",
            "trend_4h": "DOWN",
            "updated_at": "20:18:09"
        },
        "STX": {
            "val": -1.5,
            "atr": 0.0003,
            "trend_1h": "DOWN",
            "trend_4h": "DOWN",
            "updated_at": "20:18:10"
        },
        "xyz:GOLD": {
            "val": -0.27,
            "atr": 2.8357,
            "trend_1h": "DOWN",
            "trend_4h": "DOWN",
            "updated_at": "20:18:05"
        },
        "ZRO": {
            "val": -0.6,
            "atr": 0.0012,
            "trend_1h": "DOWN",
            "trend_4h": "DOWN",
            "updated_at": "20:18:08"
        },
        "xyz:BRENTOIL": {
            "val": 2.36,
            "atr": 0.2269,
            "trend_1h": "UP",
            "trend_4h": "UP",
            "updated_at": "20:18:06"
        },
        "xyz:EWY": {
            "val": -1.76,
            "atr": 0.3814,
            "trend_1h": "DOWN",
            "trend_4h": "DOWN",
            "updated_at": "20:18:07"
        },
        "xyz:SILVER": {
            "val": 0.32,
            "atr": 0.0994,
            "trend_1h": "UP",
            "trend_4h": "DOWN",
            "updated_at": "20:18:08"
        },
        "DYDX": {
            "val": -2.48,
            "atr": 0.0003,
            "trend_1h": "UP",
            "trend_4h": "UP",
            "updated_at": "20:18:10"
        }
    },
    "active_positions": {
        "xyz:EUR": {
            "side": 1,
            "entry_p": 1.1635,
            "size": 642.3,
            "entry_size": 642.3,
            "tp": 0.006,
            "sl": -0.012,
            "is_chase": false,
            "entry_time": 1780435806.5379326,
            "accumulated_pnl": 0.0,
            "tp_p": 1.17048,
            "sl_p": 1.14954,
            "effective_lev": 40.0,
            "hwm": 0.0,
            "hwm_p": 1.1635,
            "in_trail": false,
            "unrealizedPnl": -5.23,
            "roe": -7.0,
            "tp_roe": 6.0,
            "sl_roe": -12.0,
            "trail_start": 0.42,
            "trail_exit_p": 1.1621,
            "curr_p": 1.15535,
            "target_lev": 10.0
        },
        "xyz:GME": {
            "side": -1,
            "entry_p": 22.2103,
            "size": 9.76,
            "entry_size": 9.76,
            "tp": 0.012,
            "sl": -0.025,
            "is_chase": false,
            "entry_time": 1781025536.5619335,
            "accumulated_pnl": 0.0,
            "tp_p": 21.94378,
            "sl_p": 22.76556,
            "effective_lev": 10.0,
            "hwm": 0.37,
            "hwm_p": 22.1275,
            "in_trail": false,
            "unrealizedPnl": 0.49,
            "roe": 2.24,
            "tp_roe": 12.0,
            "sl_roe": -25.0,
            "trail_start": 0.84,
            "trail_exit_p": 22.1808,
            "curr_p": 22.1605,
            "target_lev": 10.0
        },
        "xyz:BRENTOIL": {
            "side": -1,
            "entry_p": 91.15,
            "size": 2.39,
            "entry_size": 2.39,
            "tp": 0.012,
            "sl": -0.025,
            "is_chase": false,
            "entry_time": 1781089499.9221163,
            "accumulated_pnl": 0.0,
            "tp_p": 90.0562,
            "sl_p": 93.42875,
            "effective_lev": 10.0,
            "hwm": 0.0,
            "hwm_p": 91.15,
            "in_trail": false,
            "unrealizedPnl": -0.48,
            "roe": -2.22,
            "tp_roe": 12.0,
            "sl_roe": -25.0,
            "trail_start": 0.84,
            "trail_exit_p": 91.36876,
            "curr_p": 91.3525,
            "target_lev": 10.0
        }
    },
    "daily_stats": {
        "pnl_usdc": 0,
        "weekly_pnl": -5.767545999999999,
        "monthly_pnl": -11.654842000000036,
        "wins": 0,
        "losses": 0,
        "asset_pnl": {},
        "date": "2026-06-10",
        "asset_losses": {}
    },
    "max_slots": 4,
    "timestamp": "2026-06-10T20:18:11.366913"
}