{
    "bot_id": "HL_INTEGRATED_MASTER",
    "equity": 75.98,
    "z_scores": {
        "xyz:BABA": {
            "val": -0.36,
            "atr": 0.0139,
            "trend_1h": "UP",
            "trend_4h": "UP",
            "updated_at": "04:12:11"
        },
        "xyz:SILVER": {
            "val": 0.46,
            "atr": 0.0319,
            "trend_1h": "UP",
            "trend_4h": "UP",
            "updated_at": "04:12:12"
        },
        "xyz:COST": {
            "val": -0.96,
            "atr": 0.0207,
            "trend_1h": "DOWN",
            "trend_4h": "DOWN",
            "updated_at": "04:12:11"
        },
        "INJ": {
            "val": 2.36,
            "atr": 0.0084,
            "trend_1h": "UP",
            "trend_4h": "DOWN",
            "updated_at": "04:12:15"
        },
        "xyz:NVDA": {
            "val": 1.08,
            "atr": 0.1193,
            "trend_1h": "UP",
            "trend_4h": "UP",
            "updated_at": "04:12:11"
        },
        "xyz:AMD": {
            "val": 1.78,
            "atr": 0.6236,
            "trend_1h": "UP",
            "trend_4h": "UP",
            "updated_at": "04:12:12"
        },
        "xyz:PLATINUM": {
            "val": 0.86,
            "atr": 0.3214,
            "trend_1h": "DOWN",
            "trend_4h": "DOWN",
            "updated_at": "04:12:13"
        },
        "FET": {
            "val": 1.2,
            "atr": 0.0001,
            "trend_1h": "UP",
            "trend_4h": "UP",
            "updated_at": "04:12:13"
        },
        "APE": {
            "val": 0.74,
            "atr": 0.0001,
            "trend_1h": "DOWN",
            "trend_4h": "DOWN",
            "updated_at": "04:12:14"
        },
        "SOL": {
            "val": 0.88,
            "atr": 0.0761,
            "trend_1h": "DOWN",
            "trend_4h": "DOWN",
            "updated_at": "04:12:14"
        },
        "DOT": {
            "val": 1.78,
            "atr": 0.0004,
            "trend_1h": "UP",
            "trend_4h": "UP",
            "updated_at": "04:12:14"
        },
        "xyz:EWJ": {
            "val": 1.43,
            "atr": 0.0027,
            "trend_1h": "UP",
            "trend_4h": "UP",
            "updated_at": "04:12:12"
        },
        "xyz:JP225": {
            "val": -0.39,
            "atr": 17.2857,
            "trend_1h": "UP",
            "trend_4h": "UP",
            "updated_at": "04:12:13"
        },
        "SUI": {
            "val": 1.45,
            "atr": 0.0006,
            "trend_1h": "UP",
            "trend_4h": "DOWN",
            "updated_at": "04:12:15"
        }
    },
    "active_positions": {},
    "daily_stats": {
        "pnl_usdc": 0,
        "weekly_pnl": -1.5917760000000012,
        "monthly_pnl": -20.409143000000007,
        "wins": 0,
        "losses": 0,
        "asset_pnl": {},
        "date": "2026-07-01",
        "asset_losses": {}
    },
    "max_slots": 4,
    "timestamp": "2026-07-01T04:12:15.406281"
}