{
    "bot_id": "HL_INTEGRATED_MASTER",
    "equity": 97.21,
    "z_scores": {
        "xyz:GOLD": {
            "val": -1.61,
            "atr": 1.1714,
            "trend_1h": "UP",
            "trend_4h": "UP",
            "updated_at": "10:00:54"
        },
        "xyz:NVDA": {
            "val": -0.01,
            "atr": 0.12,
            "trend_1h": "UP",
            "trend_4h": "DOWN",
            "updated_at": "10:00:54"
        },
        "NEO": {
            "val": 0.4,
            "atr": 0.001,
            "trend_1h": "UP",
            "trend_4h": "UP",
            "updated_at": "10:00:56"
        },
        "LDO": {
            "val": 0.52,
            "atr": 0.0003,
            "trend_1h": "UP",
            "trend_4h": "UP",
            "updated_at": "10:00:59"
        },
        "WLD": {
            "val": 0.94,
            "atr": 0.0013,
            "trend_1h": "UP",
            "trend_4h": "UP",
            "updated_at": "10:00:58"
        },
        "PENDLE": {
            "val": -0.35,
            "atr": 0.0022,
            "trend_1h": "UP",
            "trend_4h": "UP",
            "updated_at": "10:00:57"
        },
        "DYDX": {
            "val": 1.25,
            "atr": 0.0004,
            "trend_1h": "UP",
            "trend_4h": "UP",
            "updated_at": "10:00:58"
        },
        "xyz:HOOD": {
            "val": 0.23,
            "atr": 0.1599,
            "trend_1h": "UP",
            "trend_4h": "UP",
            "updated_at": "10:00:54"
        },
        "xyz:BABA": {
            "val": -1.31,
            "atr": 0.0307,
            "trend_1h": "DOWN",
            "trend_4h": "DOWN",
            "updated_at": "10:00:55"
        },
        "xyz:PLATINUM": {
            "val": -0.16,
            "atr": 0.2714,
            "trend_1h": "UP",
            "trend_4h": "UP",
            "updated_at": "10:00:55"
        },
        "xyz:INTC": {
            "val": -1.14,
            "atr": 0.0943,
            "trend_1h": "DOWN",
            "trend_4h": "DOWN",
            "updated_at": "10:00:55"
        },
        "xyz:EWJ": {
            "val": 1.6,
            "atr": 0.0296,
            "trend_1h": "UP",
            "trend_4h": "DOWN",
            "updated_at": "10:00:56"
        },
        "xyz:AMD": {
            "val": -1.55,
            "atr": 0.3786,
            "trend_1h": "DOWN",
            "trend_4h": "DOWN",
            "updated_at": "10:00:56"
        },
        "LINK": {
            "val": 0.7,
            "atr": 0.0049,
            "trend_1h": "UP",
            "trend_4h": "UP",
            "updated_at": "10:00:59"
        }
    },
    "active_positions": {
        "LINK": {
            "side": 1,
            "entry_p": 9.2201,
            "size": 24.4,
            "entry_size": 24.4,
            "tp": 0.015,
            "sl": -0.025,
            "is_chase": false,
            "entry_time": 1780178778.2223792,
            "accumulated_pnl": 0.0,
            "tp_p": 9.3584,
            "sl_p": 8.9896,
            "effective_lev": 10.0,
            "hwm": 0.0,
            "hwm_p": 9.2201,
            "in_trail": false,
            "unrealizedPnl": -1.15,
            "roe": -5.11,
            "tp_roe": 15.0,
            "sl_roe": -25.0,
            "trail_start": 0.45,
            "trail_exit_p": 9.19244,
            "curr_p": 9.173,
            "target_lev": 10.0
        }
    },
    "daily_stats": {
        "pnl_usdc": 1.740875,
        "weekly_pnl": -38.19736500000001,
        "monthly_pnl": 1.0493459999999604,
        "wins": 2,
        "losses": 0,
        "asset_pnl": {
            "PENDLE": 1.567373,
            "LDO": 0.173502
        },
        "date": "2026-06-01",
        "asset_losses": {}
    },
    "max_slots": 4,
    "timestamp": "2026-06-01T10:00:59.777704"
}