{
    "bot_id": "HL_INTEGRATED_MASTER",
    "equity": 87.79,
    "z_scores": {
        "xyz:HOOD": {
            "val": -1.09,
            "atr": 0.2464,
            "trend_1h": "DOWN",
            "trend_4h": "DOWN",
            "updated_at": "00:09:17"
        },
        "xyz:CL": {
            "val": -1.44,
            "atr": 0.0866,
            "trend_1h": "DOWN",
            "trend_4h": "UP",
            "updated_at": "00:09:17"
        },
        "DYDX": {
            "val": 0.38,
            "atr": 0.0001,
            "trend_1h": "UP",
            "trend_4h": "UP",
            "updated_at": "00:09:19"
        },
        "xyz:AMD": {
            "val": -1.18,
            "atr": 1.0643,
            "trend_1h": "UP",
            "trend_4h": "DOWN",
            "updated_at": "00:09:18"
        },
        "xyz:AAPL": {
            "val": 0.44,
            "atr": 0.2407,
            "trend_1h": "UP",
            "trend_4h": "UP",
            "updated_at": "00:09:18"
        },
        "JUP": {
            "val": -0.16,
            "atr": 0.0004,
            "trend_1h": "DOWN",
            "trend_4h": "DOWN",
            "updated_at": "00:09:19"
        },
        "xyz:GOLD": {
            "val": -0.29,
            "atr": 1.3786,
            "trend_1h": "DOWN",
            "trend_4h": "DOWN",
            "updated_at": "00:09:16"
        },
        "xyz:PLATINUM": {
            "val": -2.0,
            "atr": 1.0929,
            "trend_1h": "UP",
            "trend_4h": "DOWN",
            "updated_at": "00:09:17"
        },
        "xyz:XYZ100": {
            "val": -0.87,
            "atr": 20.7857,
            "trend_1h": "UP",
            "trend_4h": "DOWN",
            "updated_at": "00:09:18"
        },
        "xyz:SILVER": {
            "val": 0.61,
            "atr": 0.056,
            "trend_1h": "DOWN",
            "trend_4h": "DOWN",
            "updated_at": "00:09:19"
        },
        "WIF": {
            "val": 1.0,
            "atr": 0.0001,
            "trend_1h": "UP",
            "trend_4h": "UP",
            "updated_at": "00:09:19"
        },
        "INJ": {
            "val": -1.03,
            "atr": 0.0043,
            "trend_1h": "DOWN",
            "trend_4h": "DOWN",
            "updated_at": "00:09:20"
        },
        "NEAR": {
            "val": 1.03,
            "atr": 0.0042,
            "trend_1h": "UP",
            "trend_4h": "DOWN",
            "updated_at": "00:09:20"
        },
        "ARB": {
            "val": 1.36,
            "atr": 0.0001,
            "trend_1h": "UP",
            "trend_4h": "DOWN",
            "updated_at": "00:09:20"
        }
    },
    "active_positions": {},
    "daily_stats": {
        "pnl_usdc": 0,
        "weekly_pnl": 10.577955,
        "monthly_pnl": -0.9124890000000003,
        "wins": 0,
        "losses": 0,
        "asset_pnl": {},
        "date": "2026-07-17",
        "asset_losses": {}
    },
    "max_slots": 4,
    "timestamp": "2026-07-17T00:09:21.017874"
}