{
    "bot_id": "HL_INTEGRATED_MASTER",
    "equity": 95.48,
    "z_scores": {
        "xyz:HOOD": {
            "val": -0.15,
            "atr": 0.0184,
            "trend_1h": "UP",
            "trend_4h": "UP",
            "updated_at": "19:45:31"
        },
        "xyz:COPPER": {
            "val": -0.72,
            "atr": 0.0023,
            "trend_1h": "UP",
            "trend_4h": "UP",
            "updated_at": "19:45:33"
        },
        "xyz:COIN": {
            "val": 1.25,
            "atr": 0.0264,
            "trend_1h": "UP",
            "trend_4h": "UP",
            "updated_at": "19:45:33"
        },
        "UNI": {
            "val": 1.42,
            "atr": 0.0011,
            "trend_1h": "UP",
            "trend_4h": "DOWN",
            "updated_at": "19:45:28"
        },
        "LDO": {
            "val": 0.82,
            "atr": 0.0001,
            "trend_1h": "UP",
            "trend_4h": "DOWN",
            "updated_at": "19:45:29"
        },
        "PYTH": {
            "val": 1.96,
            "atr": 0.0001,
            "trend_1h": "UP",
            "trend_4h": "UP",
            "updated_at": "19:45:30"
        },
        "CRV": {
            "val": 0.9,
            "atr": 0.0001,
            "trend_1h": "UP",
            "trend_4h": "DOWN",
            "updated_at": "19:45:30"
        },
        "DOT": {
            "val": 0.11,
            "atr": 0.0005,
            "trend_1h": "UP",
            "trend_4h": "DOWN",
            "updated_at": "19:45:30"
        },
        "LINK": {
            "val": 0.6,
            "atr": 0.003,
            "trend_1h": "UP",
            "trend_4h": "DOWN",
            "updated_at": "19:45:31"
        },
        "xyz:BABA": {
            "val": -0.71,
            "atr": 0.0014,
            "trend_1h": "DOWN",
            "trend_4h": "UP",
            "updated_at": "19:45:31"
        },
        "xyz:PLATINUM": {
            "val": 1.2,
            "atr": 0.1929,
            "trend_1h": "UP",
            "trend_4h": "UP",
            "updated_at": "19:45:32"
        },
        "xyz:EWJ": {
            "val": 0.93,
            "atr": 0.0,
            "trend_1h": "DOWN",
            "trend_4h": "DOWN",
            "updated_at": "19:45:32"
        },
        "xyz:AMD": {
            "val": 0.29,
            "atr": 0.1379,
            "trend_1h": "DOWN",
            "trend_4h": "UP",
            "updated_at": "19:45:32"
        },
        "xyz:NVDA": {
            "val": -0.36,
            "atr": 0.0429,
            "trend_1h": "DOWN",
            "trend_4h": "UP",
            "updated_at": "19:45:33"
        }
    },
    "active_positions": {
        "CRV": {
            "side": -1,
            "entry_p": 0.21228,
            "size": 1161.6,
            "entry_size": 1161.6,
            "tp": 0.015,
            "sl": -0.025,
            "entry_time": 1780067466.1138952,
            "accumulated_pnl": 0.0,
            "tp_p": 0.2091,
            "sl_p": 0.21759,
            "effective_lev": 10.0,
            "hwm": 0.65,
            "hwm_p": 0.21089,
            "in_trail": false,
            "unrealizedPnl": -4.1,
            "roe": -16.63,
            "tp_roe": 15.0,
            "sl_roe": -25.0,
            "trail_start": 1.05,
            "trail_exit_p": 0.21153,
            "curr_p": 0.21581,
            "target_lev": 10.0
        },
        "UNI": {
            "side": -1,
            "entry_p": 3.02512,
            "size": 81.5,
            "entry_size": 81.5,
            "tp": 0.015,
            "sl": -0.025,
            "entry_time": 1780099791.036902,
            "accumulated_pnl": 0.0,
            "tp_p": 2.97974,
            "sl_p": 3.10075,
            "effective_lev": 10.0,
            "hwm": 0.91,
            "hwm_p": 2.9975,
            "in_trail": false,
            "unrealizedPnl": -0.59,
            "roe": -2.39,
            "tp_roe": 15.0,
            "sl_roe": -25.0,
            "trail_start": 1.05,
            "trail_exit_p": 3.00658,
            "curr_p": 3.03235,
            "target_lev": 10.0
        }
    },
    "daily_stats": {
        "pnl_usdc": -3.9182370000000004,
        "weekly_pnl": -53.144863000000015,
        "monthly_pnl": 3.131464999999951,
        "wins": 2,
        "losses": 1,
        "asset_pnl": {
            "PYTH": 0.7828470000000001,
            "LINK": -6.474581000000001,
            "LDO": 1.7734969999999999
        },
        "date": "2026-05-30",
        "asset_losses": {}
    },
    "max_slots": 4,
    "timestamp": "2026-05-30T19:45:33.880875"
}