{
    "bot_id": "HL_INTEGRATED_MASTER",
    "equity": 74.67,
    "z_scores": {
        "xyz:COST": {
            "val": -0.83,
            "atr": 0.3579,
            "trend_1h": "UP",
            "trend_4h": "DOWN",
            "updated_at": "08:55:42"
        },
        "xyz:HOOD": {
            "val": 1.48,
            "atr": 0.0429,
            "trend_1h": "UP",
            "trend_4h": "UP",
            "updated_at": "08:55:43"
        },
        "RUNE": {
            "val": -0.26,
            "atr": 0.0001,
            "trend_1h": "DOWN",
            "trend_4h": "DOWN",
            "updated_at": "08:55:40"
        },
        "IMX": {
            "val": -0.19,
            "atr": 0.0001,
            "trend_1h": "DOWN",
            "trend_4h": "DOWN",
            "updated_at": "08:55:40"
        },
        "AAVE": {
            "val": 1.11,
            "atr": 0.048,
            "trend_1h": "DOWN",
            "trend_4h": "DOWN",
            "updated_at": "08:55:39"
        },
        "TIA": {
            "val": -0.78,
            "atr": 0.0002,
            "trend_1h": "DOWN",
            "trend_4h": "DOWN",
            "updated_at": "08:55:41"
        },
        "xyz:BABA": {
            "val": 2.41,
            "atr": 0.0114,
            "trend_1h": "UP",
            "trend_4h": "DOWN",
            "updated_at": "08:55:43"
        },
        "xyz:BRENTOIL": {
            "val": -0.08,
            "atr": 0.0544,
            "trend_1h": "UP",
            "trend_4h": "UP",
            "updated_at": "08:55:39"
        },
        "xyz:PLATINUM": {
            "val": -1.78,
            "atr": 0.1929,
            "trend_1h": "DOWN",
            "trend_4h": "UP",
            "updated_at": "08:55:41"
        },
        "xyz:NATGAS": {
            "val": -0.81,
            "atr": 0.0015,
            "trend_1h": "DOWN",
            "trend_4h": "UP",
            "updated_at": "08:55:41"
        },
        "xyz:EWJ": {
            "val": 10.86,
            "atr": 0.0019,
            "trend_1h": "UP",
            "trend_4h": "DOWN",
            "updated_at": "08:55:42"
        },
        "xyz:EWY": {
            "val": 1.42,
            "atr": 0.1443,
            "trend_1h": "UP",
            "trend_4h": "UP",
            "updated_at": "08:55:42"
        }
    },
    "active_positions": {},
    "daily_stats": {
        "pnl_usdc": 0,
        "weekly_pnl": -17.521158,
        "monthly_pnl": -74.75741600000009,
        "wins": 0,
        "losses": 0,
        "asset_pnl": {},
        "date": "2026-06-20",
        "asset_losses": {}
    },
    "max_slots": 4,
    "timestamp": "2026-06-20T08:55:43.491088"
}