{
    "bot_id": "HL_INTEGRATED_MASTER",
    "equity": 77.2,
    "z_scores": {
        "xyz:COST": {
            "val": 1.92,
            "atr": 0.5007,
            "trend_1h": "DOWN",
            "trend_4h": "DOWN",
            "updated_at": "10:48:14"
        },
        "xyz:BABA": {
            "val": -2.23,
            "atr": 0.0936,
            "trend_1h": "DOWN",
            "trend_4h": "DOWN",
            "updated_at": "10:48:14"
        },
        "xyz:JP225": {
            "val": -0.14,
            "atr": 18.3571,
            "trend_1h": "UP",
            "trend_4h": "UP",
            "updated_at": "10:48:14"
        },
        "xyz:AMD": {
            "val": 1.11,
            "atr": 0.4521,
            "trend_1h": "UP",
            "trend_4h": "UP",
            "updated_at": "10:48:15"
        },
        "FET": {
            "val": 1.66,
            "atr": 0.0001,
            "trend_1h": "UP",
            "trend_4h": "UP",
            "updated_at": "10:48:16"
        },
        "xyz:PLATINUM": {
            "val": -0.71,
            "atr": 1.0143,
            "trend_1h": "DOWN",
            "trend_4h": "DOWN",
            "updated_at": "10:48:13"
        },
        "xyz:EWJ": {
            "val": -0.56,
            "atr": 0.0032,
            "trend_1h": "DOWN",
            "trend_4h": "UP",
            "updated_at": "10:48:15"
        },
        "xyz:INTC": {
            "val": 0.08,
            "atr": 0.1293,
            "trend_1h": "UP",
            "trend_4h": "UP",
            "updated_at": "10:48:15"
        },
        "xyz:MSFT": {
            "val": 1.04,
            "atr": 0.1029,
            "trend_1h": "UP",
            "trend_4h": "UP",
            "updated_at": "10:48:16"
        },
        "BCH": {
            "val": 1.76,
            "atr": 0.1286,
            "trend_1h": "UP",
            "trend_4h": "UP",
            "updated_at": "10:48:16"
        },
        "WLD": {
            "val": -2.17,
            "atr": 0.0014,
            "trend_1h": "DOWN",
            "trend_4h": "DOWN",
            "updated_at": "10:48:17"
        },
        "SOL": {
            "val": 2.11,
            "atr": 0.0621,
            "trend_1h": "UP",
            "trend_4h": "UP",
            "updated_at": "10:48:17"
        },
        "ATOM": {
            "val": 1.7,
            "atr": 0.001,
            "trend_1h": "DOWN",
            "trend_4h": "DOWN",
            "updated_at": "10:48:17"
        }
    },
    "active_positions": {},
    "daily_stats": {
        "pnl_usdc": 0,
        "weekly_pnl": -11.674007000000003,
        "monthly_pnl": -58.75560700000004,
        "wins": 0,
        "losses": 0,
        "asset_pnl": {},
        "date": "2026-06-24",
        "asset_losses": {}
    },
    "max_slots": 4,
    "timestamp": "2026-06-24T10:48:18.689222"
}