{
    "bot_id": "HL_INTEGRATED_MASTER",
    "equity": 122.41,
    "z_scores": {
        "xyz:ORCL": {
            "val": -0.14,
            "atr": 0.0714,
            "trend_1h": "UP",
            "trend_4h": "UP",
            "updated_at": "14:00:28"
        },
        "xyz:MSFT": {
            "val": -0.32,
            "atr": 0.1293,
            "trend_1h": "UP",
            "trend_4h": "UP",
            "updated_at": "14:00:28"
        },
        "CFX": {
            "val": -3.09,
            "atr": 0.0002,
            "trend_1h": "DOWN",
            "trend_4h": "DOWN",
            "updated_at": "14:00:27"
        },
        "ETH": {
            "val": -0.51,
            "atr": 0.4929,
            "trend_1h": "DOWN",
            "trend_4h": "UP",
            "updated_at": "14:00:27"
        },
        "BIGTIME": {
            "val": -1.34,
            "atr": 0.0,
            "trend_1h": "DOWN",
            "trend_4h": "DOWN",
            "updated_at": "14:00:26"
        },
        "FET": {
            "val": -1.73,
            "atr": 0.0002,
            "trend_1h": "DOWN",
            "trend_4h": "UP",
            "updated_at": "05:56:03"
        },
        "CRV": {
            "val": 0.14,
            "atr": 0.0005,
            "trend_1h": "UP",
            "trend_4h": "UP",
            "updated_at": "02:16:17"
        },
        "NEAR": {
            "val": -1.73,
            "atr": 0.0009,
            "trend_1h": "DOWN",
            "trend_4h": "UP",
            "updated_at": "14:00:27"
        },
        "xyz:BABA": {
            "val": 1.14,
            "atr": 0.0071,
            "trend_1h": "UP",
            "trend_4h": "DOWN",
            "updated_at": "14:00:28"
        },
        "xyz:HOOD": {
            "val": 0.26,
            "atr": 0.0049,
            "trend_1h": "UP",
            "trend_4h": "UP",
            "updated_at": "14:00:29"
        }
    },
    "active_positions": {
        "xyz:MSFT": {
            "side": -1,
            "entry_p": 419.48,
            "size": 0.674,
            "tp": 0.007,
            "sl": -0.03,
            "entry_time": 1778898778.369596,
            "tp_p": 416.54364,
            "sl_p": 432.0644,
            "effective_lev": 10.0,
            "hwm": 0,
            "hwm_p": 419.48,
            "in_trail": false,
            "unrealizedPnl": -0.33,
            "roe": -1.17,
            "tp_roe": 7.0,
            "sl_roe": -30.0,
            "trail_start": 0.35,
            "trail_exit_p": 420.06727,
            "curr_p": 419.97,
            "target_lev": 10.0
        }
    },
    "daily_stats": {
        "pnl_usdc": 3.8650290000000003,
        "weekly_pnl": 17.62271099999999,
        "wins": 4,
        "losses": 0,
        "asset_pnl": {
            "BIGTIME": 0.311237,
            "NEAR": 2.5043200000000003,
            "FET": 0.56134,
            "COST": 0.488132
        },
        "date": "2026-05-16",
        "asset_losses": {}
    },
    "max_slots": 4,
    "timestamp": "2026-05-16T14:00:29.362960"
}