{
    "bot_id": "HL_INTEGRATED_MASTER",
    "equity": 76.18,
    "z_scores": {
        "xyz:SILVER": {
            "val": -0.36,
            "atr": 0.0574,
            "trend_1h": "DOWN",
            "trend_4h": "DOWN",
            "updated_at": "11:44:36"
        },
        "xyz:AMD": {
            "val": -0.12,
            "atr": 0.2714,
            "trend_1h": "DOWN",
            "trend_4h": "DOWN",
            "updated_at": "11:44:38"
        },
        "xyz:PLATINUM": {
            "val": 0.48,
            "atr": 0.4214,
            "trend_1h": "DOWN",
            "trend_4h": "DOWN",
            "updated_at": "11:44:37"
        },
        "APE": {
            "val": 1.62,
            "atr": 0.0001,
            "trend_1h": "DOWN",
            "trend_4h": "DOWN",
            "updated_at": "11:44:39"
        },
        "SOL": {
            "val": 4.15,
            "atr": 0.1186,
            "trend_1h": "UP",
            "trend_4h": "UP",
            "updated_at": "11:44:39"
        },
        "DOT": {
            "val": 3.18,
            "atr": 0.0009,
            "trend_1h": "UP",
            "trend_4h": "UP",
            "updated_at": "11:44:39"
        },
        "xyz:JP225": {
            "val": -0.85,
            "atr": 9.5714,
            "trend_1h": "DOWN",
            "trend_4h": "DOWN",
            "updated_at": "11:44:37"
        },
        "xyz:SP500": {
            "val": -0.64,
            "atr": 0.7857,
            "trend_1h": "DOWN",
            "trend_4h": "DOWN",
            "updated_at": "11:44:35"
        },
        "xyz:XYZ100": {
            "val": -0.52,
            "atr": 6.1429,
            "trend_1h": "DOWN",
            "trend_4h": "DOWN",
            "updated_at": "11:44:36"
        },
        "xyz:COPPER": {
            "val": -1.0,
            "atr": 0.0007,
            "trend_1h": "DOWN",
            "trend_4h": "DOWN",
            "updated_at": "11:44:36"
        },
        "xyz:GOOGL": {
            "val": -1.28,
            "atr": 0.0464,
            "trend_1h": "DOWN",
            "trend_4h": "DOWN",
            "updated_at": "11:44:37"
        },
        "PENDLE": {
            "val": 3.46,
            "atr": 0.0017,
            "trend_1h": "UP",
            "trend_4h": "UP",
            "updated_at": "11:44:38"
        },
        "ZRO": {
            "val": 1.3,
            "atr": 0.0011,
            "trend_1h": "UP",
            "trend_4h": "UP",
            "updated_at": "11:44:38"
        },
        "CRV": {
            "val": 0.17,
            "atr": 0.0001,
            "trend_1h": "DOWN",
            "trend_4h": "DOWN",
            "updated_at": "11:44:39"
        }
    },
    "active_positions": {},
    "daily_stats": {
        "pnl_usdc": 0.233156,
        "weekly_pnl": -1.35862,
        "monthly_pnl": -20.175987,
        "wins": 1,
        "losses": 0,
        "asset_pnl": {
            "BABA": 0.233156
        },
        "date": "2026-07-01",
        "asset_losses": {}
    },
    "max_slots": 4,
    "timestamp": "2026-07-01T11:44:40.045640"
}