{
    "bot_id": "HL_INTEGRATED_MASTER",
    "equity": 73.36,
    "z_scores": {
        "xyz:AMD": {
            "val": 0.22,
            "atr": 0.3636,
            "trend_1h": "UP",
            "trend_4h": "UP",
            "updated_at": "20:37:24"
        },
        "xyz:COST": {
            "val": -1.69,
            "atr": 0.3671,
            "trend_1h": "DOWN",
            "trend_4h": "UP",
            "updated_at": "20:37:25"
        },
        "xyz:BABA": {
            "val": 0.83,
            "atr": 0.0269,
            "trend_1h": "DOWN",
            "trend_4h": "UP",
            "updated_at": "20:37:25"
        },
        "xyz:EWY": {
            "val": -1.96,
            "atr": 0.1271,
            "trend_1h": "UP",
            "trend_4h": "DOWN",
            "updated_at": "20:37:25"
        },
        "xyz:GME": {
            "val": -0.52,
            "atr": 0.0034,
            "trend_1h": "UP",
            "trend_4h": "UP",
            "updated_at": "20:37:26"
        },
        "xyz:EWJ": {
            "val": -1.94,
            "atr": 0.013,
            "trend_1h": "UP",
            "trend_4h": "DOWN",
            "updated_at": "20:37:26"
        },
        "xyz:AAPL": {
            "val": -0.06,
            "atr": 0.0229,
            "trend_1h": "DOWN",
            "trend_4h": "UP",
            "updated_at": "20:37:26"
        },
        "xyz:MSFT": {
            "val": -1.17,
            "atr": 0.0893,
            "trend_1h": "DOWN",
            "trend_4h": "UP",
            "updated_at": "20:37:27"
        },
        "FET": {
            "val": -1.96,
            "atr": 0.0001,
            "trend_1h": "DOWN",
            "trend_4h": "UP",
            "updated_at": "20:37:27"
        },
        "SOL": {
            "val": -0.85,
            "atr": 0.0429,
            "trend_1h": "UP",
            "trend_4h": "UP",
            "updated_at": "20:37:27"
        },
        "WLD": {
            "val": -1.25,
            "atr": 0.0007,
            "trend_1h": "DOWN",
            "trend_4h": "DOWN",
            "updated_at": "20:37:28"
        },
        "XRP": {
            "val": -1.67,
            "atr": 0.0003,
            "trend_1h": "UP",
            "trend_4h": "UP",
            "updated_at": "20:37:28"
        },
        "CRV": {
            "val": -0.34,
            "atr": 0.0001,
            "trend_1h": "UP",
            "trend_4h": "UP",
            "updated_at": "20:37:28"
        },
        "BCH": {
            "val": -0.08,
            "atr": 0.1007,
            "trend_1h": "UP",
            "trend_4h": "UP",
            "updated_at": "20:37:29"
        }
    },
    "active_positions": {},
    "daily_stats": {
        "pnl_usdc": -4.792038,
        "weekly_pnl": -16.885094,
        "monthly_pnl": -62.59091600000006,
        "wins": 0,
        "losses": 1,
        "asset_pnl": {
            "JP225": -4.792038
        },
        "date": "2026-06-25",
        "asset_losses": {}
    },
    "max_slots": 4,
    "timestamp": "2026-06-25T20:37:29.369438"
}