{
    "bot_id": "HL_INTEGRATED_MASTER",
    "equity": 73.15,
    "z_scores": {
        "xyz:SILVER": {
            "val": -0.95,
            "atr": 0.0491,
            "trend_1h": "DOWN",
            "trend_4h": "DOWN",
            "updated_at": "09:41:15"
        },
        "APE": {
            "val": 0.66,
            "atr": 0.0001,
            "trend_1h": "DOWN",
            "trend_4h": "DOWN",
            "updated_at": "09:41:18"
        },
        "DOT": {
            "val": -2.0,
            "atr": 0.0006,
            "trend_1h": "DOWN",
            "trend_4h": "DOWN",
            "updated_at": "09:41:17"
        },
        "xyz:JP225": {
            "val": -1.6,
            "atr": 46.2857,
            "trend_1h": "DOWN",
            "trend_4h": "DOWN",
            "updated_at": "09:41:16"
        },
        "xyz:SP500": {
            "val": 0.21,
            "atr": 1.3857,
            "trend_1h": "DOWN",
            "trend_4h": "DOWN",
            "updated_at": "09:41:14"
        },
        "xyz:XYZ100": {
            "val": -0.16,
            "atr": 12.6429,
            "trend_1h": "DOWN",
            "trend_4h": "DOWN",
            "updated_at": "09:41:14"
        },
        "PENDLE": {
            "val": 1.27,
            "atr": 0.0032,
            "trend_1h": "UP",
            "trend_4h": "UP",
            "updated_at": "09:41:17"
        },
        "ZRO": {
            "val": -2.13,
            "atr": 0.0011,
            "trend_1h": "DOWN",
            "trend_4h": "DOWN",
            "updated_at": "09:41:16"
        },
        "CRV": {
            "val": 0.39,
            "atr": 0.0005,
            "trend_1h": "UP",
            "trend_4h": "UP",
            "updated_at": "09:41:17"
        },
        "xyz:NVDA": {
            "val": -0.29,
            "atr": 0.1393,
            "trend_1h": "DOWN",
            "trend_4h": "DOWN",
            "updated_at": "09:41:13"
        },
        "xyz:CL": {
            "val": -1.79,
            "atr": 0.0264,
            "trend_1h": "DOWN",
            "trend_4h": "DOWN",
            "updated_at": "09:41:14"
        },
        "xyz:ORCL": {
            "val": 0.32,
            "atr": 0.0457,
            "trend_1h": "DOWN",
            "trend_4h": "DOWN",
            "updated_at": "09:41:15"
        },
        "xyz:BABA": {
            "val": -1.17,
            "atr": 0.0139,
            "trend_1h": "DOWN",
            "trend_4h": "UP",
            "updated_at": "09:41:16"
        },
        "INJ": {
            "val": -2.22,
            "atr": 0.0061,
            "trend_1h": "DOWN",
            "trend_4h": "DOWN",
            "updated_at": "09:41:18"
        }
    },
    "active_positions": {
        "xyz:JP225": {
            "side": 1,
            "entry_p": 70414.4,
            "size": 0.00257,
            "entry_size": 0.00257,
            "tp": 0.012,
            "sl": -0.025,
            "is_chase": false,
            "entry_time": 1782887328.9835076,
            "accumulated_pnl": 0.0,
            "tp_p": 71259.3728,
            "sl_p": 68654.04,
            "effective_lev": 10.0,
            "hwm": 0.0,
            "hwm_p": 70414.4,
            "in_trail": false,
            "unrealizedPnl": -3.63,
            "roe": -20.07,
            "tp_roe": 12.0,
            "sl_roe": -25.0,
            "trail_start": 0.84,
            "trail_exit_p": 70245.40544,
            "curr_p": 69001.5,
            "target_lev": 10.0
        }
    },
    "daily_stats": {
        "pnl_usdc": 0,
        "weekly_pnl": -2.3309830000000002,
        "monthly_pnl": -17.453039,
        "wins": 0,
        "losses": 0,
        "asset_pnl": {},
        "date": "2026-07-02",
        "asset_losses": {}
    },
    "max_slots": 4,
    "timestamp": "2026-07-02T09:41:18.388476"
}