{
    "bot_id": "HL_INTEGRATED_MASTER",
    "equity": 119.52,
    "z_scores": {
        "xyz:ORCL": {
            "val": -1.23,
            "atr": 0.125,
            "trend_1h": "DOWN",
            "trend_4h": "UP",
            "updated_at": "05:35:03"
        },
        "xyz:MSFT": {
            "val": -1.44,
            "atr": 0.25,
            "trend_1h": "DOWN",
            "trend_4h": "UP",
            "updated_at": "05:35:03"
        },
        "CFX": {
            "val": 1.38,
            "atr": 0.0,
            "trend_1h": "UP",
            "trend_4h": "UP",
            "updated_at": "05:35:02"
        },
        "ETH": {
            "val": -1.29,
            "atr": 1.1357,
            "trend_1h": "DOWN",
            "trend_4h": "UP",
            "updated_at": "05:35:02"
        },
        "BIGTIME": {
            "val": -1.39,
            "atr": 0.0,
            "trend_1h": "DOWN",
            "trend_4h": "UP",
            "updated_at": "05:35:01"
        },
        "FET": {
            "val": -1.27,
            "atr": 0.0001,
            "trend_1h": "DOWN",
            "trend_4h": "UP",
            "updated_at": "05:35:02"
        },
        "CRV": {
            "val": 0.14,
            "atr": 0.0005,
            "trend_1h": "UP",
            "trend_4h": "UP",
            "updated_at": "02:16:17"
        },
        "NEAR": {
            "val": -1.62,
            "atr": 0.0014,
            "trend_1h": "DOWN",
            "trend_4h": "UP",
            "updated_at": "05:35:01"
        },
        "xyz:BABA": {
            "val": -1.24,
            "atr": 0.0207,
            "trend_1h": "DOWN",
            "trend_4h": "DOWN",
            "updated_at": "05:35:03"
        },
        "xyz:HOOD": {
            "val": -1.32,
            "atr": 0.008,
            "trend_1h": "DOWN",
            "trend_4h": "UP",
            "updated_at": "05:35:04"
        }
    },
    "active_positions": {
        "FET": {
            "side": -1,
            "entry_p": 0.20395,
            "size": 698.0,
            "tp": 0.015,
            "sl": -0.025,
            "entry_time": 1778862119.5712922,
            "tp_p": 0.20089,
            "sl_p": 0.20905,
            "effective_lev": 5.0,
            "hwm": 0.28,
            "hwm_p": 0.203385,
            "in_trail": false,
            "unrealizedPnl": -0.02,
            "roe": -0.06,
            "tp_roe": 7.5,
            "sl_roe": -12.5,
            "trail_start": 0.75,
            "trail_exit_p": 0.204,
            "curr_p": 0.203975,
            "target_lev": 5
        },
        "BIGTIME": {
            "side": -1,
            "entry_p": 0.013053,
            "size": 6519.0,
            "tp": 0.015,
            "sl": -0.025,
            "entry_time": 1778862678.8475816,
            "tp_p": 0.01286,
            "sl_p": 0.01338,
            "effective_lev": 3.0,
            "hwm": 0.47,
            "hwm_p": 0.012991,
            "in_trail": false,
            "unrealizedPnl": 0.25,
            "roe": 0.87,
            "tp_roe": 4.5,
            "sl_roe": -7.5,
            "trail_start": 0.75,
            "trail_exit_p": 0.01303,
            "curr_p": 0.013015,
            "target_lev": 3
        }
    },
    "daily_stats": {
        "pnl_usdc": 0.488132,
        "weekly_pnl": 14.171982999999997,
        "wins": 1,
        "losses": 0,
        "asset_pnl": {
            "COST": 0.488132
        },
        "date": "2026-05-16",
        "asset_losses": {}
    },
    "max_slots": 4,
    "timestamp": "2026-05-16T05:35:04.337192"
}